notion_tools.py
notion_tools-0.1.2.dist-info/LICENSE
notion_tools-0.1.2.dist-info/WHEEL
notion_tools-0.1.2.dist-info/METADATA
notion_tools-0.1.2.dist-info/RECORD
