Metadata-Version: 2.1
Name: notion-tools
Version: 0.1.2
Summary: Python and pandas helpers for Notion
License: Apache-2.0
Author: Patch Biosciences, Inc.
Author-email: contact@patch.bio
Requires-Python: >=3.6
Classifier: License :: OSI Approved :: Apache Software License
Classifier: Programming Language :: Python :: 3
Classifier: Programming Language :: Python :: 3.10
Classifier: Programming Language :: Python :: 3.6
Classifier: Programming Language :: Python :: 3.7
Classifier: Programming Language :: Python :: 3.8
Classifier: Programming Language :: Python :: 3.9
Requires-Dist: notion-client (>=0.4)
Requires-Dist: pandas (>=1.0)
